[
  {
    "name": "demo",
    "id": "0123",
    "addr": "test",
    "cases": [
      {
        "meta": {
          "year": 2019,
          "month": 1,
          "day": 23,
          "addr": "Nanjing"
        },
        "title": "title demo",
        "content": "content lorem ipssum"
      },
      {
        "meta": {
          "year": 2019,
          "month": 1,
          "day": 23,
          "addr": "Nanjing"
        },
        "title": "title demo",
        "content": "content lorem ipsum"
      }
    ]
  }
]
